IsaREPL/IsaREPL.py
IsaREPL/__init__.py
isarepl-0.11.2.dist-info/licenses/COPYING.LESSER.txt
isarepl-0.11.2.dist-info/licenses/COPYING.txt
isarepl-0.11.2.dist-info/licenses/LICENSE
isarepl-0.11.2.dist-info/METADATA
isarepl-0.11.2.dist-info/WHEEL
isarepl-0.11.2.dist-info/top_level.txt
isarepl-0.11.2.dist-info/RECORD
