Metadata-Version: 2.4
Name: IsaREPL
Version: 0.11.2
Summary: Isabelle REPL client
Author-email: Qiyuan Xu <xqyww123@gmail.com>
License-Expression: LGPL-2.1-or-later
Project-URL: Homepage, https://github.com/xqyww123/Isa-REPL
Classifier: Programming Language :: Python :: 3
Classifier: Operating System :: OS Independent
License-File: LICENSE
License-File: COPYING.LESSER.txt
License-File: COPYING.txt
Requires-Dist: msgpack
Dynamic: license-file
